pytinytask-3.2.dist-info/licenses/LICENSE
tinytask/__init__.py
tinytask/main.py
tinytask/old_main.py
tinytask/src/play.png
tinytask/src/play2.png
tinytask/src/replay.png
tinytask/src/replay2.png
tinytask/src/stop.png
tinytask/src/stop2.png
tinytask/src/x.png
tinytask/src/x2.png
pytinytask-3.2.dist-info/METADATA
pytinytask-3.2.dist-info/WHEEL
pytinytask-3.2.dist-info/entry_points.txt
pytinytask-3.2.dist-info/top_level.txt
pytinytask-3.2.dist-info/RECORD
