Metadata-Version: 2.4
Name: pytinytask
Version: 3.2
Summary: A simple macro recording and replaying tool
Home-page: https://github.com/SmartBoyMuzaffar/tinytask
Author: Smart Boy
Classifier: License :: OSI Approved :: MIT License
Classifier: Programming Language :: Python
Classifier: Programming Language :: Python :: 3
Classifier: Programming Language :: Python :: 3.6
Classifier: Programming Language :: Python :: 3.7
Classifier: Programming Language :: Python :: 3.8
Classifier: Programming Language :: Python :: 3.9
Classifier: Programming Language :: Python :: 3.10
Classifier: Programming Language :: Python :: 3.11
Classifier: Programming Language :: Python :: 3.12
Classifier: Programming Language :: Python :: 3.13
Classifier: Programming Language :: Python :: 3.14
Classifier: Operating System :: Microsoft :: Windows
Classifier: Operating System :: POSIX :: Linux
Requires-Python: >=3.6
License-File: LICENSE
Requires-Dist: customtkinter==5.2.2
Requires-Dist: darkdetect==0.8.0
Requires-Dist: keyboard==0.13.5
Requires-Dist: mouse==0.7.1
Requires-Dist: packaging==24.2
Requires-Dist: pillow
Requires-Dist: setuptools==75.8.0
Requires-Dist: wheel==0.45.1
Dynamic: author
Dynamic: classifier
Dynamic: description
Dynamic: description-content-type
Dynamic: home-page
Dynamic: license-file
Dynamic: requires-dist
Dynamic: requires-python
Dynamic: summary
